gender_identification/__init__.py
gender_identification/__main__.py
gender_identification/cli.py
gender_identification/inference.py
gender_identification-0.1.0.dist-info/LICENSE
gender_identification-0.1.0.dist-info/METADATA
gender_identification-0.1.0.dist-info/WHEEL
gender_identification-0.1.0.dist-info/RECORD
